{
	"name": "ds_gold_dim_cliente",
	"properties": {
		"linkedServiceName": {
			"referenceName": "ls_sql_ventas_examen",
			"type": "LinkedServiceReference"
		},
		"folder": {
			"name": "Gold"
		},
		"annotations": [],
		"type": "AzureSqlTable",
		"schema": [
			{
				"name": "id_cliente",
				"type": "int",
				"precision": 10
			},
			{
				"name": "cst_id",
				"type": "int",
				"precision": 10
			},
			{
				"name": "cst_firstname",
				"type": "nvarchar"
			},
			{
				"name": "cst_lastname",
				"type": "nvarchar"
			},
			{
				"name": "cst_marital_status",
				"type": "nvarchar"
			},
			{
				"name": "birthdate",
				"type": "date"
			},
			{
				"name": "gender",
				"type": "nvarchar"
			},
			{
				"name": "country",
				"type": "nvarchar"
			}
		],
		"typeProperties": {
			"schema": "gold",
			"table": "dim_cliente"
		}
	},
	"type": "Microsoft.DataFactory/factories/datasets"
}